<annotation>
	<folder>raw_images</folder>
	<filename>cows_images_162.jpg</filename>
	<path>/home/nbh/Desktop/cow_detection/cow_detection/raw_images/cows_images_162.jpg</path>
	<source>
		<database>Unknown</database>
	</source>
	<size>
		<width>360</width>
		<height>240</height>
		<depth>3</depth>
	</size>
	<segmented>0</segmented>
	<object>
		<name>cow</name>
		<pose>Unspecified</pose>
		<truncated>0</truncated>
		<difficult>0</difficult>
		<bndbox>
			<xmin>98</xmin>
			<ymin>137</ymin>
			<xmax>169</xmax>
			<ymax>208</ymax>
		</bndbox>
	</object>
	<object>
		<name>cow</name>
		<pose>Unspecified</pose>
		<truncated>0</truncated>
		<difficult>0</difficult>
		<bndbox>
			<xmin>173</xmin>
			<ymin>140</ymin>
			<xmax>226</xmax>
			<ymax>207</ymax>
		</bndbox>
	</object>
	<object>
		<name>cow</name>
		<pose>Unspecified</pose>
		<truncated>1</truncated>
		<difficult>0</difficult>
		<bndbox>
			<xmin>225</xmin>
			<ymin>109</ymin>
			<xmax>360</xmax>
			<ymax>209</ymax>
		</bndbox>
	</object>
</annotation>
